[
  {
    "nome": "1984",
    "autores": [
      { "nome": "George Orwell", "email": "ifsp@mail.com", "genero": "M" },
      { "nome": "Miguel de Cervantes", "email": "ifsp@mail.com", "genero": "F" }
    ],
    "quantidade": 1,
    "price": 2
  },

  {
    "nome": "Orgulho e Preconceito",
    "autores": [
      { "nome": "Jane Austen", "email": "ifsp@mail.com", "genero": "F" },
      { "nome": "George Orwell", "email": "ifsp@mail.com", "genero": "M" }
    ],
    "quantidade": 0,
    "price": 0
  },

  {
    "nome": "Por Lugares Incríveis",
    "autores": [
      { "nome": "Jennifer Niven", "email": "ifsp@mail.com", "genero": "F" },
      {
        "email": "ifsp@mail.com",
        "genero": "M",
        "nome": "Antoine de Saint-Exupéry"
      }
    ],
    "quantidade": 2,
    "preco": 4
  },
  
  {
    "nome": "O Pequeno Príncipe",
    "autores": [
      {
        "nome": "Antoine de Saint-Exupéry",
        "email": "ifsp@mail.com",
        "genero": "M"
      },
      { "nome": "Machado de Assis", "email": "ifsp@mail.com", "genero": "F" }
    ],
    "quantidade": 3,
    "price": 1
  }
]
